{
  "timestamp": "2025-11-11T09:58:38.548685",
  "fear_greed": {
    "value": 26,
    "classification": "Fear",
    "timestamp": "1762819200",
    "history_7d": [
      26,
      29,
      22,
      20,
      24,
      27,
      23
    ]
  },
  "global_market": {
    "total_market_cap_usd": 3626585304620.659,
    "total_volume_24h_usd": 197082285799.6934,
    "btc_dominance": 57.737357084434535,
    "eth_dominance": 11.835327775133957,
    "active_cryptocurrencies": 19412
  },
  "bitcoin": {
    "price_usd": 104955,
    "volume_24h_usd": 69962042434.45374,
    "price_change_24h": -1.4002625133751845
  },
  "top_movers": {
    "gainers": [
      {
        "symbol": "UNI",
        "name": "Uniswap",
        "price_change_24h": 19.42261
      },
      {
        "symbol": "FIGR_HELOC",
        "name": "Figure Heloc",
        "price_change_24h": 1.77701
      },
      {
        "symbol": "XAUT",
        "name": "Tether Gold",
        "price_change_24h": 1.51079
      },
      {
        "symbol": "PAXG",
        "name": "PAX Gold",
        "price_change_24h": 1.50167
      }
    ],
    "losers": [
      {
        "symbol": "NEAR",
        "name": "NEAR Protocol",
        "price_change_24h": -11.75954
      },
      {
        "symbol": "ICP",
        "name": "Internet Computer",
        "price_change_24h": -11.99749
      },
      {
        "symbol": "ZEC",
        "name": "Zcash",
        "price_change_24h": -26.32088
      },
      {
        "symbol": "CC",
        "name": "Canton",
        "price_change_24h": -28.82229
      }
    ]
  },
  "market_breadth": 21.0
}